{
  "heroTitle": "Get Your Free Estimate",
  "heroSubtitle": "Fast quotes. Professional pressure washing & soft washing.",
  "heroBg": "/pictures/Washology/Gemini_Generated_Image_5t5p1o5t5p1o5t5p.png",
  "leftTitle": "Start Your Exterior Cleaning",
  "leftSubtitle": "Pressure washing & soft washing done right.",
  "leftBg": "/pictures/Washology/Gemini_Generated_Image_gl6ufrgl6ufrgl6u.png",
  "bullet1": "HOUSE & SIDING WASH",
  "bullet2": "ROOF SOFT WASH",
  "bullet3": "DRIVEWAYS & CONCRETE",
  "bullet4": "GUTTER WHITENING",
  "bullet5": "FENCE & DECK CLEANING",
  "bullet6": "COMMERCIAL WASHING",
  "rightTitle": "Estimates in 24 Hours or Less",
  "bottomTitle": "Get An Estimate",
  "reviewsTitle": "Discover our 5-Star Reputation",
  "review1Text": "Great company! Very reliable and professional. Our driveway and patio look brand new.",
  "review1Author": "Barry Kramer",
  "review2Text": "The team did an amazing job and worked around the rain. Super happy with the results!",
  "review2Author": "Paul Flavion",
  "review3Text": "Washology soft-washed our roof and cleaned the concrete—night and day difference. Professional and thorough.",
  "review3Author": "Michelle Morrison",
  "ctaTitle": "Ready to get started?",
  "ctaBody": "Contact us for a free onsite estimate within 24 hours.",
  "ctaLabel": "Contact Us",
  "ctaUrl": "/contact-us"
}